IteratorAlgorithms.py
IteratorAlgorithms-0.1.6.dist-info/METADATA
IteratorAlgorithms-0.1.6.dist-info/WHEEL
IteratorAlgorithms-0.1.6.dist-info/top_level.txt
IteratorAlgorithms-0.1.6.dist-info/RECORD
