Metadata-Version: 2.1
Name: IteratorAlgorithms
Version: 0.1.6
Summary: A collection of iterator algorithms for Python3.
Home-page: UNKNOWN
Author: Robert Sharp
Author-email: webmaster@sharpdesigndigital.com
License: UNKNOWN
Keywords: accumulate,adjacent_difference,all_of,any_of,difference,exclusive_scan,fork,generate,generate_n,inclusive_scan,inner_product,intersection,iota,min_max,none_of,partial_sum,partition,product,reduce,star_sum,star_product,symmetric_difference,transform,transform_reduce,transposed_sums,union,zip_transform
Platform: UNKNOWN
Classifier: Development Status :: 4 - Beta
Classifier: Programming Language :: Python :: 3.8
Classifier: Topic :: Software Development :: Libraries :: Python Modules
Requires-Python: >=3.6
